adduserpath-0.4.0.dist-info/DESCRIPTION.rst
adduserpath-0.4.0.dist-info/METADATA
adduserpath-0.4.0.dist-info/RECORD
adduserpath-0.4.0.dist-info/WHEEL
adduserpath-0.4.0.dist-info/entry_points.txt
adduserpath-0.4.0.dist-info/metadata.json
adduserpath-0.4.0.dist-info/top_level.txt
tests/__init__.py
tests/test_core.py
userpath/__init__.py
userpath/__main__.py
userpath/cli.py
userpath/core.py
